<?xml version="1.0" encoding="UTF-8"?>
<!DOCTYPE QuickLink PUBLIC "sailpoint.dtd" "sailpoint.dtd">
<QuickLink action="workflow" category="Admin" cssClass="quicklink-ldapcreate" messageKey="Create New Group" name="COB-QuickLink-CreateROFIDGrp">
  <Attributes>
    <Map>
      <entry key="workflowName" value="COB-Workflow-CreateROFIDGroup"/>
      <entry key="workflowSuccess" value="Starting ROFID Group Request Process..."/>
    </Map>
  </Attributes>
  <QuickLinkOptions allowSelf="true">
    <DynamicScopeRef>
      <Reference class="sailpoint.object.DynamicScope" name="COB-DynamicScope-GroupAdmins"/>
    </DynamicScopeRef>
  </QuickLinkOptions>
</QuickLink>
